xcomposite/__init__.py
xcomposite/core.py
xcomposite/decorators.py
xcomposite/tests/__init__.py
xcomposite/tests/classes.py
xcomposite/tests/test_composition.py
xcomposite/tests/test_decorators.py
xcomposite-2.0.8.dist-info/licenses/LICENSE
xcomposite-2.0.8.dist-info/METADATA
xcomposite-2.0.8.dist-info/WHEEL
xcomposite-2.0.8.dist-info/top_level.txt
xcomposite-2.0.8.dist-info/RECORD
