Metadata-Version: 2.4
Name: xcomposite
Version: 2.0.8
Summary: A python package exposing the class composition design pattern
Home-page: https://github.com/mikemalinowski/xcomposite
Author: Mike Malinowski
Author-email: mike.malinowski@outlook.com
Keywords: xcomposite composite composition inheritance side combine
Classifier: Programming Language :: Python
Classifier: License :: OSI Approved :: MIT License
Classifier: Operating System :: OS Independent
License-File: LICENSE
Dynamic: author
Dynamic: author-email
Dynamic: classifier
Dynamic: description
Dynamic: description-content-type
Dynamic: home-page
Dynamic: keywords
Dynamic: license-file
Dynamic: summary
